py_midicsv/__init__.py
py_midicsv/cli.py
py_midicsv/csv_converters.py
py_midicsv/csvmidi.py
py_midicsv/events.py
py_midicsv/midi/__init__.py
py_midicsv/midi/constants.py
py_midicsv/midi/containers.py
py_midicsv/midi/events.py
py_midicsv/midi/fileio.py
py_midicsv/midi/util.py
py_midicsv/midi_converters.py
py_midicsv/midicsv.py
py_midicsv-4.1.1.dist-info/LICENSE
py_midicsv-4.1.1.dist-info/METADATA
py_midicsv-4.1.1.dist-info/WHEEL
py_midicsv-4.1.1.dist-info/entry_points.txt
py_midicsv-4.1.1.dist-info/RECORD
